convertmask/__init__.py
convertmask/convertmaskUI_v_0_5_any.py
convertmask/main_v_0_3_any.py
convertmask/main_v_0_5_any.py
convertmask/labelme_sub/__init__.py
convertmask/labelme_sub/__main__.py
convertmask/labelme_sub/app.py
convertmask/labelme_sub/label_file.py
convertmask/labelme_sub/logger.py
convertmask/labelme_sub/shape.py
convertmask/labelme_sub/testing.py
convertmask/labelme_sub/cli/__init__.py
convertmask/labelme_sub/cli/draw_json.py
convertmask/labelme_sub/cli/draw_label_png.py
convertmask/labelme_sub/cli/json_to_dataset.py
convertmask/labelme_sub/cli/on_docker.py
convertmask/labelme_sub/config/__init__.py
convertmask/labelme_sub/utils/__init__.py
convertmask/labelme_sub/utils/_io.py
convertmask/labelme_sub/utils/draw.py
convertmask/labelme_sub/utils/image.py
convertmask/labelme_sub/utils/qt.py
convertmask/labelme_sub/utils/shape.py
convertmask/labelme_sub/widgets/__init__.py
convertmask/labelme_sub/widgets/canvas.py
convertmask/labelme_sub/widgets/color_dialog.py
convertmask/labelme_sub/widgets/escapable_qlist_widget.py
convertmask/labelme_sub/widgets/label_dialog.py
convertmask/labelme_sub/widgets/label_list_widget.py
convertmask/labelme_sub/widgets/tool_bar.py
convertmask/labelme_sub/widgets/unique_label_qlist_widget.py
convertmask/labelme_sub/widgets/zoom_widget.py
convertmask/utils/__init__.py
convertmask/utils/imgAug_script.py
convertmask/utils/mask2json_script.py
convertmask/utils/auglib/OperatorWithoutLabel.py
convertmask/utils/auglib/__init__.py
convertmask/utils/auglib/imgAug.py
convertmask/utils/auglib/imgAug_nolabel.py
convertmask/utils/auglib/imgAug_xmls.py
convertmask/utils/auglib/optionsOperatorWithoutLabel.py
convertmask/utils/auglib/optional/Operator.py
convertmask/utils/auglib/optional/__init__.py
convertmask/utils/auglib/optional/crop.py
convertmask/utils/auglib/optional/cutmix.py
convertmask/utils/auglib/optional/cutout.py
convertmask/utils/auglib/optional/distort.py
convertmask/utils/auglib/optional/generatePolygon.py
convertmask-0.5.3.dist-info/LICENSE
convertmask-0.5.3.dist-info/METADATA
convertmask-0.5.3.dist-info/WHEEL
convertmask-0.5.3.dist-info/entry_points.txt
convertmask-0.5.3.dist-info/top_level.txt
convertmask-0.5.3.dist-info/zip-safe
convertmask-0.5.3.dist-info/RECORD
