Metadata-Version: 2.1
Name: convertmask
Version: 0.5.3
Summary: a small tool for image augmentation, including mask files to json/xml files , image augmentation(flip,rotation,noise,...) and so on
Home-page: https://github.com/guchengxi1994/mask2json
Author: Chengxi GU
Author-email: guchengxi1994@qq.com
License: Apache License
Platform: UNKNOWN
Classifier: Programming Language :: Python
Classifier: Programming Language :: Python :: 3.7
Classifier: Programming Language :: Python :: 3.6
Requires-Dist: labelme (==4.2.9)
Requires-Dist: numpy (==1.18.4)
Requires-Dist: opencv-python (==4.1.0.25)
Requires-Dist: xmltodict (==0.12.0)
Requires-Dist: matplotlib (==3.1.0)
Requires-Dist: scikit-image (==0.15.0)
Requires-Dist: Pillow (==7.1.2)
Requires-Dist: PyYAML (==5.3.1)
Requires-Dist: scipy (==1.5.1)
Requires-Dist: termcolor (==1.1.0)
Requires-Dist: lxml (>=4.6.2)
Requires-Dist: tqdm (==4.32.1)
